{"name":"Gulp-jsonify-images","tagline":"Gulp plugin to create base64 string from images and write them into json file","body":"# gulp-jsonify-images\r\n\r\n## Run command\r\n```\r\nnpm i -D gulp-jsonify-images\r\n```\r\n\r\n## Usage\r\n```js\r\nvar gulp = require('gulp');\r\nvar jsonImages = require('gulp-jsonify-images');\r\n\r\ngulp.task('default', function() {\r\n    gulp.src('./src/images/*.png')\r\n        .pipe(jsonImages({\r\n            path: './dist/assets/store',\r\n            filename: 'data.json',\r\n            type: 'base64'\r\n        }))\r\n        .pipe(gulp.dest('./dist/assets/images'));\r\n});\r\n```\r\n\r\n## Options\r\n- **path** - destination to store file\r\n- **filename** - name of the json file\r\n- **type** - base64/utf8 or other string compressors\r\n","google":"","note":"Don't delete this file! It's used internally to help with page regeneration."}